fullmetalcopy/__init__.py
fullmetalcopy/drivers.py
fullmetalcopy/names.py
fullmetalcopy/query.py
fullmetalcopy/asynchronous/__init__.py
fullmetalcopy/asynchronous/copycsv.py
fullmetalcopy/synchronous/__init__.py
fullmetalcopy/synchronous/copycsv.py
fullmetalcopy-0.1.0.dist-info/LICENSE
fullmetalcopy-0.1.0.dist-info/METADATA
fullmetalcopy-0.1.0.dist-info/WHEEL
fullmetalcopy-0.1.0.dist-info/top_level.txt
fullmetalcopy-0.1.0.dist-info/RECORD
